ctr/__init__.py
ctr/Crawler/__init__.py
ctr/Crawler/crawl_confluence.py
ctr/Database/__init__.py
ctr/Database/connection.py
ctr/Database/model.py
ctr/Reporting/Dash.py
ctr/Reporting/DashPages.py
ctr/Reporting/DashValues.py
ctr/Reporting/Reporter.py
ctr/Reporting/__init__.py
ctr/Util/Config.py
ctr/Util/Util.py
ctr/Util/__init__.py
tests/__init__.py
tests/prefill_database.py
tests/test_0_database_model.py
tests/test_crawler_tasks.py
tests/test_crawler_users.py
tests/test_reporting.py
Confluence_Task_Crawler-0.0.6.dist-info/LICENSE
Confluence_Task_Crawler-0.0.6.dist-info/METADATA
Confluence_Task_Crawler-0.0.6.dist-info/WHEEL
Confluence_Task_Crawler-0.0.6.dist-info/top_level.txt
Confluence_Task_Crawler-0.0.6.dist-info/RECORD
