Metadata-Version: 2.1
Name: Confluence-Task-Crawler
Version: 0.0.6
Summary: Task Crawler and Reporter with Dashboard for Atlassian Confluence On-Prem Installations
Home-page: https://www.buhl-consulting.com.cy
Author: Bernhard Buhl
Author-email: buhl@buhl-consulting.com.cy
License: UNKNOWN
Platform: UNKNOWN
Classifier: Programming Language :: Python :: 3
Classifier: License :: OSI Approved :: MIT License
Classifier: Operating System :: OS Independent
Requires-Python: >=3.6
Requires-Dist: atlassian-python-api (>=3.25.0)
Requires-Dist: BeautifulSoup4 (>=4.11.1)
Requires-Dist: dash (>=2.5.1)
Requires-Dist: dash-bootstrap-components (>=1.1.0)
Requires-Dist: pandas (>=1.4.2)
Requires-Dist: python-dotenv (>=0.20.0)
Requires-Dist: sqlalchemy (>=1.4.37)
Requires-Dist: toml (>=0.10.2)
Requires-Dist: xlsxwriter (>=3.0.3)
